{
  "identifier": "",
  "motion_text": "HOUSE K-12 SUBCOMMITTEE: Rec for pass if am by s/c ref. to Education Committee  3/24/2026  Passed",
  "motion_classification": [
    "passage"
  ],
  "start_date": "2026-03-24",
  "result": "pass",
  "organization": "~{\"classification\": \"lower\"}",
  "legislative_session": "114",
  "bill": "c18122de-75d5-11f1-a848-024fd3a6aad0",
  "bill_action": null,
  "bill_identifier": "HB 0640",
  "votes": [],
  "counts": [
    {
      "option": "yes",
      "value": 8
    },
    {
      "option": "no",
      "value": 0
    },
    {
      "option": "not voting",
      "value": 0
    }
  ],
  "sources": [
    {
      "url": "https://wapp.capitol.tn.gov/apps/BillInfo/Default?BillNumber=HB0640&ga=114",
      "note": ""
    }
  ],
  "extras": {}
}