{
  "identifier": "",
  "motion_text": "HOUSE CRIMINAL JUSTICE SUBCOMMITTEE: Rec. for pass by s/c ref. to Judiciary Committee  3/25/2026  Passed (2)",
  "motion_classification": [
    "passage"
  ],
  "start_date": "2026-03-25",
  "result": "pass",
  "organization": "~{\"classification\": \"lower\"}",
  "legislative_session": "114",
  "bill": "b7cc7e58-75d7-11f1-a848-024fd3a6aad0",
  "bill_action": null,
  "bill_identifier": "HR 0143",
  "votes": [
    {
      "option": "not voting",
      "voter_name": "Atchley",
      "voter_id": "~{\"name\": \"Atchley\"}",
      "note": ""
    },
    {
      "option": "not voting",
      "voter_name": "Doggett",
      "voter_id": "~{\"name\": \"Doggett\"}",
      "note": ""
    },
    {
      "option": "not voting",
      "voter_name": "Farmer",
      "voter_id": "~{\"name\": \"Farmer\"}",
      "note": ""
    },
    {
      "option": "not voting",
      "voter_name": "Lamberth",
      "voter_id": "~{\"name\": \"Lamberth\"}",
      "note": ""
    },
    {
      "option": "not voting",
      "voter_name": "Littleton",
      "voter_id": "~{\"name\": \"Littleton\"}",
      "note": ""
    },
    {
      "option": "not voting",
      "voter_name": "Russell",
      "voter_id": "~{\"name\": \"Russell\"}",
      "note": ""
    },
    {
      "option": "not voting",
      "voter_name": "Scarbrough",
      "voter_id": "~{\"name\": \"Scarbrough\"}",
      "note": ""
    }
  ],
  "counts": [
    {
      "option": "yes",
      "value": 2
    },
    {
      "option": "no",
      "value": 0
    },
    {
      "option": "not voting",
      "value": 7
    }
  ],
  "sources": [
    {
      "url": "https://wapp.capitol.tn.gov/apps/BillInfo/Default?BillNumber=HR0143&ga=114",
      "note": ""
    }
  ],
  "extras": {}
}