{
  "identifier": "",
  "motion_text": "FLOOR VOTE: REGULAR CALENDAR    MOTION TO ADOPT  4/6/2026  Passed (1)",
  "motion_classification": [
    "passage"
  ],
  "start_date": "2026-04-06",
  "result": "pass",
  "organization": "~{\"classification\": \"lower\"}",
  "legislative_session": "114",
  "bill": "72f9d866-75d7-11f1-a848-024fd3a6aad0",
  "bill_action": null,
  "bill_identifier": "HJR 1218",
  "votes": [
    {
      "option": "not voting",
      "voter_name": "Clemmons",
      "voter_id": "~{\"name\": \"Clemmons\"}",
      "note": ""
    },
    {
      "option": "not voting",
      "voter_name": "Glynn",
      "voter_id": "~{\"name\": \"Glynn\"}",
      "note": ""
    },
    {
      "option": "not voting",
      "voter_name": "Hemmer",
      "voter_id": "~{\"name\": \"Hemmer\"}",
      "note": ""
    },
    {
      "option": "not voting",
      "voter_name": "Mitchell",
      "voter_id": "~{\"name\": \"Mitchell\"}",
      "note": ""
    }
  ],
  "counts": [
    {
      "option": "yes",
      "value": 75
    },
    {
      "option": "no",
      "value": 14
    },
    {
      "option": "not voting",
      "value": 4
    }
  ],
  "sources": [
    {
      "url": "https://wapp.capitol.tn.gov/apps/BillInfo/Default?BillNumber=HJR1218&ga=114",
      "note": ""
    }
  ],
  "extras": {}
}