{
  "identifier": "",
  "motion_text": "HOUSE FINANCE, WAYS, AND MEANS SUBCOMMITTEE: Rec. for pass by s/c ref. to  Finance, Ways, and Means Committee  4/14/2025  Passed (3)",
  "motion_classification": [
    "passage"
  ],
  "start_date": "2025-04-14",
  "result": "pass",
  "organization": "~{\"classification\": \"lower\"}",
  "legislative_session": "114",
  "bill": "92b8b20a-75d5-11f1-a848-024fd3a6aad0",
  "bill_action": null,
  "bill_identifier": "HB 0381",
  "votes": [
    {
      "option": "not voting",
      "voter_name": "Capley",
      "voter_id": "~{\"name\": \"Capley\"}",
      "note": ""
    }
  ],
  "counts": [
    {
      "option": "yes",
      "value": 8
    },
    {
      "option": "no",
      "value": 2
    },
    {
      "option": "not voting",
      "value": 1
    }
  ],
  "sources": [
    {
      "url": "https://wapp.capitol.tn.gov/apps/BillInfo/Default?BillNumber=HB0381&ga=114",
      "note": ""
    }
  ],
  "extras": {}
}