{
  "identifier": "",
  "motion_text": "FLOOR VOTE: REGULAR CALENDAR    PASSAGE ON THIRD CONSIDERATION  4/3/2025  Failed",
  "motion_classification": [
    "passage"
  ],
  "start_date": "2025-04-03",
  "result": "fail",
  "organization": "~{\"classification\": \"lower\"}",
  "legislative_session": "114",
  "bill": "95471cfc-75d3-11f1-a848-024fd3a6aad0",
  "bill_action": null,
  "bill_identifier": "SB 0766",
  "votes": [
    {
      "option": "not voting",
      "voter_name": "Capley",
      "voter_id": "~{\"name\": \"Capley\"}",
      "note": ""
    },
    {
      "option": "not voting",
      "voter_name": "Gant",
      "voter_id": "~{\"name\": \"Gant\"}",
      "note": ""
    },
    {
      "option": "not voting",
      "voter_name": "Hale",
      "voter_id": "~{\"name\": \"Hale\"}",
      "note": ""
    },
    {
      "option": "not voting",
      "voter_name": "Haston",
      "voter_id": "~{\"name\": \"Haston\"}",
      "note": ""
    },
    {
      "option": "not voting",
      "voter_name": "Hemmer",
      "voter_id": "~{\"name\": \"Hemmer\"}",
      "note": ""
    },
    {
      "option": "not voting",
      "voter_name": "Hulsey",
      "voter_id": "~{\"name\": \"Hulsey\"}",
      "note": ""
    },
    {
      "option": "not voting",
      "voter_name": "Hurt",
      "voter_id": "~{\"name\": \"Hurt\"}",
      "note": ""
    },
    {
      "option": "not voting",
      "voter_name": "Lafferty",
      "voter_id": "~{\"name\": \"Lafferty\"}",
      "note": ""
    },
    {
      "option": "not voting",
      "voter_name": "Littleton",
      "voter_id": "~{\"name\": \"Littleton\"}",
      "note": ""
    },
    {
      "option": "not voting",
      "voter_name": "Rudd",
      "voter_id": "~{\"name\": \"Rudd\"}",
      "note": ""
    },
    {
      "option": "not voting",
      "voter_name": "Rudder",
      "voter_id": "~{\"name\": \"Rudder\"}",
      "note": ""
    },
    {
      "option": "not voting",
      "voter_name": "Sherrell",
      "voter_id": "~{\"name\": \"Sherrell\"}",
      "note": ""
    },
    {
      "option": "not voting",
      "voter_name": "Terry",
      "voter_id": "~{\"name\": \"Terry\"}",
      "note": ""
    },
    {
      "option": "not voting",
      "voter_name": "Vital",
      "voter_id": "~{\"name\": \"Vital\"}",
      "note": ""
    }
  ],
  "counts": [
    {
      "option": "yes",
      "value": 48
    },
    {
      "option": "no",
      "value": 27
    },
    {
      "option": "not voting",
      "value": 14
    }
  ],
  "sources": [
    {
      "url": "https://wapp.capitol.tn.gov/apps/BillInfo/Default?BillNumber=SB0766&ga=114",
      "note": ""
    }
  ],
  "extras": {}
}