{
  "legislative_session": "114",
  "identifier": "HB 1823",
  "title": "Local Education Agencies - As enacted, requires a director of schools to refer to juvenile court certain students who were formerly enrolled in the LEA, who were receiving certain truancy interventions, who withdrew from the LEA, and who did not transfer to another LEA; makes related changes. - Amends TCA Title 37, Chapter 1, Part 1; Title 49, Chapter 1; Title 49, Chapter 2 and Title 49, Chapter 6.",
  "from_organization": "~{\"classification\": \"lower\"}",
  "classification": [
    "bill"
  ],
  "subject": [
    "Local Education Agencies"
  ],
  "abstracts": [],
  "other_titles": [],
  "other_identifiers": [
    {
      "identifier": "ocd-bill-tn-114-hb1823"
    }
  ],
  "actions": [
    {
      "description": "Filed for introduction",
      "date": "2026-01-21",
      "organization_id": "~{\"classification\": \"lower\"}",
      "classification": [
        "filing"
      ],
      "related_entities": [],
      "_processing": {
        "log_file_created": "2026-07-13T06:05:30Z"
      }
    },
    {
      "description": "Intro., P1C.",
      "date": "2026-01-22",
      "organization_id": "~{\"classification\": \"lower\"}",
      "classification": [
        "introduction"
      ],
      "related_entities": [],
      "_processing": {
        "log_file_created": "2026-07-13T06:05:30Z"
      }
    },
    {
      "description": "Assigned to s/c Education Administration Subcommittee",
      "date": "2026-02-02",
      "organization_id": "~{\"classification\": \"lower\"}",
      "classification": [
        "referral-committee"
      ],
      "related_entities": [],
      "_processing": {
        "log_file_created": "2026-07-13T06:05:30Z"
      }
    },
    {
      "description": "P2C, ref. to Education Committee",
      "date": "2026-02-02",
      "organization_id": "~{\"classification\": \"lower\"}",
      "classification": [
        "referral-committee"
      ],
      "related_entities": [],
      "_processing": {
        "log_file_created": "2026-07-13T06:05:30Z"
      }
    },
    {
      "description": "Placed on s/c cal Education Administration Subcommittee for 3/3/2026",
      "date": "2026-02-25",
      "organization_id": "~{\"classification\": \"lower\"}",
      "classification": [],
      "related_entities": [],
      "_processing": {
        "log_file_created": "2026-07-13T06:05:30Z"
      }
    },
    {
      "description": "Rec for pass if am by s/c ref. to Education Committee",
      "date": "2026-03-03",
      "organization_id": "~{\"classification\": \"lower\"}",
      "classification": [
        "referral-committee"
      ],
      "related_entities": [],
      "_processing": {
        "log_file_created": "2026-07-13T06:05:30Z"
      }
    },
    {
      "description": "Placed on cal. Education Committee for 3/10/2026",
      "date": "2026-03-04",
      "organization_id": "~{\"classification\": \"lower\"}",
      "classification": [],
      "related_entities": [],
      "_processing": {
        "log_file_created": "2026-07-13T06:05:30Z"
      }
    },
    {
      "description": "Action def. in Education Committee to 3/17/2026",
      "date": "2026-03-10",
      "organization_id": "~{\"classification\": \"lower\"}",
      "classification": [],
      "related_entities": [],
      "_processing": {
        "log_file_created": "2026-07-13T06:05:30Z"
      }
    },
    {
      "description": "Placed on cal. Education Committee for 3/17/2026",
      "date": "2026-03-11",
      "organization_id": "~{\"classification\": \"lower\"}",
      "classification": [],
      "related_entities": [],
      "_processing": {
        "log_file_created": "2026-07-13T06:05:30Z"
      }
    },
    {
      "description": "Action def. in Education Committee to 3/24/2026",
      "date": "2026-03-17",
      "organization_id": "~{\"classification\": \"lower\"}",
      "classification": [],
      "related_entities": [],
      "_processing": {
        "log_file_created": "2026-07-13T06:05:30Z"
      }
    },
    {
      "description": "Placed on cal. Education Committee for 3/24/2026",
      "date": "2026-03-18",
      "organization_id": "~{\"classification\": \"lower\"}",
      "classification": [],
      "related_entities": [],
      "_processing": {
        "log_file_created": "2026-07-13T06:05:30Z"
      }
    },
    {
      "description": "Placed on cal. Education Committee for 3/31/2026",
      "date": "2026-03-25",
      "organization_id": "~{\"classification\": \"lower\"}",
      "classification": [],
      "related_entities": [],
      "_processing": {
        "log_file_created": "2026-07-13T06:05:30Z"
      }
    },
    {
      "description": "Action def. in Education Committee to 4/1/2026",
      "date": "2026-03-25",
      "organization_id": "~{\"classification\": \"lower\"}",
      "classification": [],
      "related_entities": [],
      "_processing": {
        "log_file_created": "2026-07-13T06:05:30Z"
      }
    },
    {
      "description": "Rec. for pass. if am., ref. to  Calendar & Rules Committee",
      "date": "2026-04-01",
      "organization_id": "~{\"classification\": \"lower\"}",
      "classification": [
        "committee-passage-favorable"
      ],
      "related_entities": [],
      "_processing": {
        "log_file_created": "2026-07-13T06:05:30Z"
      }
    },
    {
      "description": "Sponsor(s) Added.",
      "date": "2026-04-06",
      "organization_id": "~{\"classification\": \"lower\"}",
      "classification": [
        "sponsorship"
      ],
      "related_entities": [],
      "_processing": {
        "log_file_created": "2026-07-13T06:05:30Z"
      }
    },
    {
      "description": "Placed on cal. Calendar & Rules Committee for 4/9/2026",
      "date": "2026-04-08",
      "organization_id": "~{\"classification\": \"lower\"}",
      "classification": [],
      "related_entities": [],
      "_processing": {
        "log_file_created": "2026-07-13T06:05:30Z"
      }
    },
    {
      "description": "H. Placed on Regular Calendar for 4/13/2026",
      "date": "2026-04-09",
      "organization_id": "~{\"classification\": \"lower\"}",
      "classification": [],
      "related_entities": [],
      "_processing": {
        "log_file_created": "2026-07-13T06:05:30Z"
      }
    },
    {
      "description": "Comp. SB subst.",
      "date": "2026-04-15",
      "organization_id": "~{\"classification\": \"lower\"}",
      "classification": [],
      "related_entities": [],
      "_processing": {
        "log_file_created": "2026-07-13T06:05:30Z"
      }
    },
    {
      "description": "Comp. became Pub. Ch. 844",
      "date": "2026-05-05",
      "organization_id": "~{\"classification\": \"lower\"}",
      "classification": [],
      "related_entities": [],
      "_processing": {
        "log_file_created": "2026-07-13T06:05:30Z"
      }
    }
  ],
  "sponsorships": [
    {
      "name": "Raper",
      "classification": "primary",
      "entity_type": "person",
      "primary": true,
      "person_id": "~{\"name\": \"Raper\"}",
      "organization_id": null
    }
  ],
  "related_bills": [
    {
      "identifier": "SB 1968",
      "legislative_session": "114",
      "relation_type": "companion"
    }
  ],
  "versions": [
    {
      "note": "Current Version",
      "links": [
        {
          "url": "https://capitol.tn.gov/Bills/114/Bill/HB1823.pdf",
          "media_type": "application/pdf"
        }
      ],
      "date": "",
      "classification": ""
    },
    {
      "note": "Amendment HA1024",
      "links": [
        {
          "url": "https://capitol.tn.gov/Bills/114/Amend/HA1024.pdf",
          "media_type": "application/pdf"
        }
      ],
      "date": "",
      "classification": ""
    },
    {
      "note": "Amendment HA1129",
      "links": [
        {
          "url": "https://capitol.tn.gov/Bills/114/Amend/HA1129.pdf",
          "media_type": "application/pdf"
        }
      ],
      "date": "",
      "classification": ""
    },
    {
      "note": "Amendment SA0542",
      "links": [
        {
          "url": "https://capitol.tn.gov/Bills/114/Amend/SA0542.pdf",
          "media_type": "application/pdf"
        }
      ],
      "date": "",
      "classification": ""
    }
  ],
  "documents": [
    {
      "note": "Fiscal Note",
      "links": [
        {
          "url": "https://capitol.tn.gov/Bills/114/Fiscal/HB1823.pdf",
          "media_type": ""
        }
      ],
      "date": "",
      "classification": ""
    },
    {
      "note": "Fiscal Memo for HA1024 (13377)",
      "links": [
        {
          "url": "https://capitol.tn.gov/Bills/114/Fiscal/FM1772.pdf",
          "media_type": ""
        }
      ],
      "date": "",
      "classification": ""
    }
  ],
  "citations": [],
  "sources": [
    {
      "url": "https://wapp.capitol.tn.gov/apps/BillInfo/Default?BillNumber=HB1823&ga=114",
      "note": ""
    }
  ],
  "extras": {},
  "jurisdiction": {
    "id": "ocd-jurisdiction/country:us/state:tn/government",
    "name": "Tennessee",
    "classification": "state",
    "division_id": "ocd-division/country:us/state:tn"
  },
  "_processing": {
    "logs_latest_update": "2026-07-21T07:57:15Z",
    "text_extraction_latest_update": "2026-07-21T15:33:25.614793Z"
  }
}