{
  "legislative_session": "114",
  "identifier": "HB 1783",
  "title": "Courts, Juvenile - As introduced, requires the department of children's services, and others, to provide certain information to court-appointed special advocates in order to provide judicial officers with the most comprehensive information to be used in the consideration of the placement and custody of a child. - Amends TCA Title 37, Chapter 1, Part 1.",
  "from_organization": "~{\"classification\": \"lower\"}",
  "classification": [
    "bill"
  ],
  "subject": [
    "Courts",
    "Juvenile"
  ],
  "abstracts": [],
  "other_titles": [],
  "other_identifiers": [
    {
      "identifier": "ocd-bill-tn-114-hb1783"
    }
  ],
  "actions": [
    {
      "description": "Filed for introduction",
      "date": "2026-01-20",
      "organization_id": "~{\"classification\": \"lower\"}",
      "classification": [
        "filing"
      ],
      "related_entities": [],
      "_processing": {
        "log_file_created": "2026-07-13T06:05:27Z"
      }
    },
    {
      "description": "Sponsor change.",
      "date": "2026-01-21",
      "organization_id": "~{\"classification\": \"lower\"}",
      "classification": [
        "sponsorship"
      ],
      "related_entities": [],
      "_processing": {
        "log_file_created": "2026-07-13T06:05:27Z"
      }
    },
    {
      "description": "Sponsor(s) Added.",
      "date": "2026-01-21",
      "organization_id": "~{\"classification\": \"lower\"}",
      "classification": [
        "sponsorship"
      ],
      "related_entities": [],
      "_processing": {
        "log_file_created": "2026-07-13T06:05:27Z"
      }
    },
    {
      "description": "Intro., P1C.",
      "date": "2026-01-22",
      "organization_id": "~{\"classification\": \"lower\"}",
      "classification": [
        "introduction"
      ],
      "related_entities": [],
      "_processing": {
        "log_file_created": "2026-07-13T06:05:27Z"
      }
    },
    {
      "description": "Assigned to s/c Children and Family Affairs Subcommittee",
      "date": "2026-02-02",
      "organization_id": "~{\"classification\": \"lower\"}",
      "classification": [
        "referral-committee"
      ],
      "related_entities": [],
      "_processing": {
        "log_file_created": "2026-07-13T06:05:27Z"
      }
    },
    {
      "description": "P2C, ref. to Judiciary Committee",
      "date": "2026-02-02",
      "organization_id": "~{\"classification\": \"lower\"}",
      "classification": [
        "referral-committee"
      ],
      "related_entities": [],
      "_processing": {
        "log_file_created": "2026-07-13T06:05:27Z"
      }
    }
  ],
  "sponsorships": [
    {
      "name": "Butler",
      "classification": "primary",
      "entity_type": "person",
      "primary": true,
      "person_id": "~{\"name\": \"Butler\"}",
      "organization_id": null
    }
  ],
  "related_bills": [
    {
      "identifier": "SB 1755",
      "legislative_session": "114",
      "relation_type": "companion"
    }
  ],
  "versions": [
    {
      "note": "Current Version",
      "links": [
        {
          "url": "https://capitol.tn.gov/Bills/114/Bill/HB1783.pdf",
          "media_type": "application/pdf"
        }
      ],
      "date": "",
      "classification": ""
    }
  ],
  "documents": [],
  "citations": [],
  "sources": [
    {
      "url": "https://wapp.capitol.tn.gov/apps/BillInfo/Default?BillNumber=HB1783&ga=114",
      "note": ""
    }
  ],
  "extras": {},
  "jurisdiction": {
    "id": "ocd-jurisdiction/country:us/state:tn/government",
    "name": "Tennessee",
    "classification": "state",
    "division_id": "ocd-division/country:us/state:tn"
  },
  "_processing": {
    "logs_latest_update": "2026-07-13T06:05:27Z",
    "text_extraction_latest_update": "2026-07-13T12:55:34.061583Z"
  }
}