{
  "identifier": "",
  "motion_text": "HOUSE FINANCE, WAYS, AND MEANS COMMITTEE: Rec. for pass; ref to  Calendar & Rules Committee  4/17/2025  Passed (2)",
  "motion_classification": [
    "passage"
  ],
  "start_date": "2025-04-17",
  "result": "pass",
  "organization": "~{\"classification\": \"lower\"}",
  "legislative_session": "114",
  "bill": "b212910c-75d5-11f1-a848-024fd3a6aad0",
  "bill_action": null,
  "bill_identifier": "HB 0541",
  "votes": [
    {
      "option": "not voting",
      "voter_name": "Camper",
      "voter_id": "~{\"name\": \"Camper\"}",
      "note": ""
    },
    {
      "option": "not voting",
      "voter_name": "Love",
      "voter_id": "~{\"name\": \"Love\"}",
      "note": ""
    }
  ],
  "counts": [
    {
      "option": "yes",
      "value": 24
    },
    {
      "option": "no",
      "value": 1
    },
    {
      "option": "not voting",
      "value": 2
    }
  ],
  "sources": [
    {
      "url": "https://wapp.capitol.tn.gov/apps/BillInfo/Default?BillNumber=HB0541&ga=114",
      "note": ""
    }
  ],
  "extras": {}
}