{
  "identifier": "",
  "motion_text": "HOUSE HEALTH COMMITTEE: Rec. for pass. if am., ref. to  Government Operations Committee  3/24/2026  Passed (3)",
  "motion_classification": [
    "passage"
  ],
  "start_date": "2026-03-24",
  "result": "pass",
  "organization": "~{\"classification\": \"lower\"}",
  "legislative_session": "114",
  "bill": "a6aeab06-75d6-11f1-a848-024fd3a6aad0",
  "bill_action": null,
  "bill_identifier": "HB 2290",
  "votes": [
    {
      "option": "not voting",
      "voter_name": "Mitchell",
      "voter_id": "~{\"name\": \"Mitchell\"}",
      "note": ""
    }
  ],
  "counts": [
    {
      "option": "yes",
      "value": 15
    },
    {
      "option": "no",
      "value": 5
    },
    {
      "option": "not voting",
      "value": 1
    }
  ],
  "sources": [
    {
      "url": "https://wapp.capitol.tn.gov/apps/BillInfo/Default?BillNumber=HB2290&ga=114",
      "note": ""
    }
  ],
  "extras": {}
}