{
  "legislative_session": "114",
  "identifier": "HB 0701",
  "title": "Utilities, Utility Districts - As introduced, removes the requirement that each year the Tennessee public utility commission submit to the general assembly a report describing the competitive nature of the telecommunications market in this state. - Amends TCA Title 65, Chapter 1 and Title 65, Chapter 5.",
  "from_organization": "~{\"classification\": \"lower\"}",
  "classification": [
    "bill"
  ],
  "subject": [
    "Utilities",
    "Utility Districts"
  ],
  "abstracts": [],
  "other_titles": [],
  "other_identifiers": [
    {
      "identifier": "ocd-bill-tn-114-hb701"
    }
  ],
  "actions": [
    {
      "description": "Filed for introduction",
      "date": "2025-02-03",
      "organization_id": "~{\"classification\": \"lower\"}",
      "classification": [
        "filing"
      ],
      "related_entities": [],
      "_processing": {
        "log_file_created": "2026-07-13T06:05:29Z"
      }
    },
    {
      "description": "Intro., P1C.",
      "date": "2025-02-05",
      "organization_id": "~{\"classification\": \"lower\"}",
      "classification": [
        "introduction"
      ],
      "related_entities": [],
      "_processing": {
        "log_file_created": "2026-07-13T06:05:29Z"
      }
    },
    {
      "description": "P2C, caption bill, held on desk - pending amdt.",
      "date": "2025-02-06",
      "organization_id": "~{\"classification\": \"lower\"}",
      "classification": [],
      "related_entities": [],
      "_processing": {
        "log_file_created": "2026-07-13T06:05:29Z"
      }
    },
    {
      "description": "Sponsor change.",
      "date": "2026-02-05",
      "organization_id": "~{\"classification\": \"lower\"}",
      "classification": [
        "sponsorship"
      ],
      "related_entities": [],
      "_processing": {
        "log_file_created": "2026-07-13T06:05:29Z"
      }
    }
  ],
  "sponsorships": [
    {
      "name": "Marsh",
      "classification": "primary",
      "entity_type": "person",
      "primary": true,
      "person_id": "~{\"name\": \"Marsh\"}",
      "organization_id": null
    }
  ],
  "related_bills": [
    {
      "identifier": "SB 983",
      "legislative_session": "114",
      "relation_type": "companion"
    }
  ],
  "versions": [
    {
      "note": "Current Version",
      "links": [
        {
          "url": "https://capitol.tn.gov/Bills/114/Bill/HB0701.pdf",
          "media_type": "application/pdf"
        }
      ],
      "date": "",
      "classification": ""
    }
  ],
  "documents": [
    {
      "note": "Fiscal Note",
      "links": [
        {
          "url": "https://capitol.tn.gov/Bills/114/Fiscal/HB0701.pdf",
          "media_type": ""
        }
      ],
      "date": "",
      "classification": ""
    }
  ],
  "citations": [],
  "sources": [
    {
      "url": "https://wapp.capitol.tn.gov/apps/BillInfo/Default?BillNumber=HB0701&ga=114",
      "note": ""
    }
  ],
  "extras": {},
  "jurisdiction": {
    "id": "ocd-jurisdiction/country:us/state:tn/government",
    "name": "Tennessee",
    "classification": "state",
    "division_id": "ocd-division/country:us/state:tn"
  },
  "_processing": {
    "logs_latest_update": "2026-07-13T06:05:29Z",
    "text_extraction_latest_update": "2026-07-13T17:26:57.318029Z"
  }
}