{
  "identifier": "",
  "motion_text": "SENATE JUDICIARY COMMITTEE: Recommended for passage with amendment/s, refer to Senate Finance, Ways, and Means Committee Ayes 8, Nays 0 PNV 0  4/8/2025  Passed",
  "motion_classification": [
    "passage"
  ],
  "start_date": "2025-04-08",
  "result": "pass",
  "organization": "~{\"classification\": \"upper\"}",
  "legislative_session": "114",
  "bill": "6877f37c-75d3-11f1-a848-024fd3a6aad0",
  "bill_action": null,
  "bill_identifier": "SB 0445",
  "votes": [],
  "counts": [
    {
      "option": "yes",
      "value": 8
    },
    {
      "option": "no",
      "value": 0
    },
    {
      "option": "not voting",
      "value": 0
    }
  ],
  "sources": [
    {
      "url": "https://wapp.capitol.tn.gov/apps/BillInfo/Default?BillNumber=SB0445&ga=114",
      "note": ""
    }
  ],
  "extras": {}
}