{
  "identifier": "",
  "motion_text": "SENATE GOVERNMENT OPERATIONS COMMITTEE: Recommended for passage, refer to Senate Commerce and Labor Committee  2/18/2026  Passed (3)",
  "motion_classification": [
    "passage"
  ],
  "start_date": "2026-02-18",
  "result": "pass",
  "organization": "~{\"classification\": \"upper\"}",
  "legislative_session": "114",
  "bill": "5eb56b7a-75d4-11f1-a848-024fd3a6aad0",
  "bill_action": null,
  "bill_identifier": "SB 2224",
  "votes": [],
  "counts": [
    {
      "option": "yes",
      "value": 6
    },
    {
      "option": "no",
      "value": 2
    },
    {
      "option": "not voting",
      "value": 0
    }
  ],
  "sources": [
    {
      "url": "https://wapp.capitol.tn.gov/apps/BillInfo/Default?BillNumber=SB2224&ga=114",
      "note": ""
    }
  ],
  "extras": {}
}