{
  "legislative_session": "114",
  "identifier": "HB 1863",
  "title": "Lottery, Scholarships and Programs - As introduced, requires the Tennessee higher education commission to submit a report to the education and finance committees of the senate and house of representatives identifying any fiscal year, beginning with the 2004 fiscal year, for which net lottery proceeds were insufficient to fully fund certain scholarships and grants, resulting in a pro rata reduction in award amounts or a draw upon the general shortfall reserve subaccount. - Amends TCA Title 4, Chapter 49; Title 4, Chapter 51 and Title 49, Chapter 4.",
  "from_organization": "~{\"classification\": \"lower\"}",
  "classification": [
    "bill"
  ],
  "subject": [
    "Lottery",
    "Scholarships and Programs"
  ],
  "abstracts": [],
  "other_titles": [],
  "other_identifiers": [
    {
      "identifier": "ocd-bill-tn-114-hb1863"
    }
  ],
  "actions": [
    {
      "description": "Filed for introduction",
      "date": "2026-01-21",
      "organization_id": "~{\"classification\": \"lower\"}",
      "classification": [
        "filing"
      ],
      "related_entities": [],
      "_processing": {
        "log_file_created": "2026-07-13T06:05:35Z"
      }
    },
    {
      "description": "Intro., P1C.",
      "date": "2026-01-22",
      "organization_id": "~{\"classification\": \"lower\"}",
      "classification": [
        "introduction"
      ],
      "related_entities": [],
      "_processing": {
        "log_file_created": "2026-07-13T06:05:35Z"
      }
    },
    {
      "description": "Assigned to s/c Higher Education Subcommittee",
      "date": "2026-02-02",
      "organization_id": "~{\"classification\": \"lower\"}",
      "classification": [
        "referral-committee"
      ],
      "related_entities": [],
      "_processing": {
        "log_file_created": "2026-07-13T06:05:35Z"
      }
    },
    {
      "description": "P2C, ref. to Education Committee",
      "date": "2026-02-02",
      "organization_id": "~{\"classification\": \"lower\"}",
      "classification": [
        "referral-committee"
      ],
      "related_entities": [],
      "_processing": {
        "log_file_created": "2026-07-13T06:05:35Z"
      }
    }
  ],
  "sponsorships": [
    {
      "name": "Hicks G",
      "classification": "primary",
      "entity_type": "person",
      "primary": true,
      "person_id": "~{\"name\": \"Hicks G\"}",
      "organization_id": null
    }
  ],
  "related_bills": [
    {
      "identifier": "SB 2078",
      "legislative_session": "114",
      "relation_type": "companion"
    }
  ],
  "versions": [
    {
      "note": "Current Version",
      "links": [
        {
          "url": "https://capitol.tn.gov/Bills/114/Bill/HB1863.pdf",
          "media_type": "application/pdf"
        }
      ],
      "date": "",
      "classification": ""
    }
  ],
  "documents": [
    {
      "note": "Fiscal Note",
      "links": [
        {
          "url": "https://capitol.tn.gov/Bills/114/Fiscal/HB1863.pdf",
          "media_type": ""
        }
      ],
      "date": "",
      "classification": ""
    }
  ],
  "citations": [],
  "sources": [
    {
      "url": "https://wapp.capitol.tn.gov/apps/BillInfo/Default?BillNumber=HB1863&ga=114",
      "note": ""
    }
  ],
  "extras": {},
  "jurisdiction": {
    "id": "ocd-jurisdiction/country:us/state:tn/government",
    "name": "Tennessee",
    "classification": "state",
    "division_id": "ocd-division/country:us/state:tn"
  },
  "_processing": {
    "logs_latest_update": "2026-07-13T06:05:35Z",
    "text_extraction_latest_update": "2026-07-21T16:03:47.507252Z"
  }
}