{
  "legislative_session": "114",
  "identifier": "SB 2301",
  "title": "Education, Dept. of - As introduced, enacts the \"School Mental Health Transparency Act\"; requires the department to consult relevant agencies to compile a list of mental health resources; requires public schools to use the department's list to compile lists of mental health resources available to enrolled students and provide the lists to students' parents; requires that lists of mental health resources be published on the website of the department and each public school. - Amends TCA Title 10, Chapter 7; Title 33 and Title 49.",
  "from_organization": "~{\"classification\": \"upper\"}",
  "classification": [
    "bill"
  ],
  "subject": [
    "Dept. of",
    "Education"
  ],
  "abstracts": [],
  "other_titles": [],
  "other_identifiers": [
    {
      "identifier": "ocd-bill-tn-114-sb2301"
    }
  ],
  "actions": [
    {
      "description": "Introduced, Passed on First Consideration",
      "date": "2026-02-02",
      "organization_id": "~{\"classification\": \"lower\"}",
      "classification": [
        "introduction"
      ],
      "related_entities": [],
      "_processing": {
        "log_file_created": "2026-07-13T06:05:27Z"
      }
    },
    {
      "description": "Filed for introduction",
      "date": "2026-02-02",
      "organization_id": "~{\"classification\": \"lower\"}",
      "classification": [
        "filing"
      ],
      "related_entities": [],
      "_processing": {
        "log_file_created": "2026-07-13T06:05:27Z"
      }
    },
    {
      "description": "Passed on Second Consideration, refer to Senate Education Committee",
      "date": "2026-02-05",
      "organization_id": "~{\"classification\": \"upper\"}",
      "classification": [
        "referral-committee"
      ],
      "related_entities": [],
      "_processing": {
        "log_file_created": "2026-07-13T06:05:27Z"
      }
    },
    {
      "description": "Placed on Senate Education Committee calendar for 3/4/2026",
      "date": "2026-02-26",
      "organization_id": "~{\"classification\": \"lower\"}",
      "classification": [],
      "related_entities": [],
      "_processing": {
        "log_file_created": "2026-07-13T06:05:27Z"
      }
    },
    {
      "description": "Sponsor(s) Added.",
      "date": "2026-03-02",
      "organization_id": "~{\"classification\": \"lower\"}",
      "classification": [
        "sponsorship"
      ],
      "related_entities": [],
      "_processing": {
        "log_file_created": "2026-07-13T06:05:27Z"
      }
    },
    {
      "description": "Assigned to General Subcommittee of Senate Education Committee",
      "date": "2026-03-04",
      "organization_id": "~{\"classification\": \"lower\"}",
      "classification": [
        "referral-committee"
      ],
      "related_entities": [],
      "_processing": {
        "log_file_created": "2026-07-13T06:05:27Z"
      }
    }
  ],
  "sponsorships": [
    {
      "name": "Oliver",
      "classification": "primary",
      "entity_type": "person",
      "primary": true,
      "person_id": "~{\"name\": \"Oliver\"}",
      "organization_id": null
    }
  ],
  "related_bills": [
    {
      "identifier": "HB 2003",
      "legislative_session": "114",
      "relation_type": "companion"
    }
  ],
  "versions": [
    {
      "note": "Current Version",
      "links": [
        {
          "url": "https://capitol.tn.gov/Bills/114/Bill/SB2301.pdf",
          "media_type": "application/pdf"
        }
      ],
      "date": "",
      "classification": ""
    }
  ],
  "documents": [
    {
      "note": "Fiscal Note",
      "links": [
        {
          "url": "https://capitol.tn.gov/Bills/114/Fiscal/HB2003.pdf",
          "media_type": ""
        }
      ],
      "date": "",
      "classification": ""
    }
  ],
  "citations": [],
  "sources": [
    {
      "url": "https://wapp.capitol.tn.gov/apps/BillInfo/Default?BillNumber=SB2301&ga=114",
      "note": ""
    }
  ],
  "extras": {},
  "jurisdiction": {
    "id": "ocd-jurisdiction/country:us/state:tn/government",
    "name": "Tennessee",
    "classification": "state",
    "division_id": "ocd-division/country:us/state:tn"
  },
  "_processing": {
    "logs_latest_update": "2026-07-13T06:05:27Z"
  }
}